slack_messenger/__init__.py
slack_messenger/slack_messenger.py
slack_messenger-0.1.1.dist-info/LICENSE
slack_messenger-0.1.1.dist-info/METADATA
slack_messenger-0.1.1.dist-info/WHEEL
slack_messenger-0.1.1.dist-info/top_level.txt
slack_messenger-0.1.1.dist-info/RECORD
