Metadata-Version: 2.1
Name: slack-messenger
Version: 0.1.1
Summary: Slack Messanger Client using Incoming Webhooks
Home-page: https://github.com/LouieT/slack-messenger
Author: Louis Tadman
Author-email: <noreply@louistadman.com>
License: UNKNOWN
Project-URL: Documentation, https://github.com/LouieT/slack-messenger
Project-URL: Source, https://github.com/LouieT/slack-messenger
Keywords: python,Slack,Messenger
Platform: UNKNOWN
Classifier: Development Status :: 3 - Alpha
Classifier: Intended Audience :: Developers
Classifier: Programming Language :: Python :: 3
Classifier: Programming Language :: Python :: 3.8
Classifier: Programming Language :: Python :: 3.9
Classifier: Programming Language :: Python :: 3.10
Classifier: Programming Language :: Python :: 3.11
Classifier: Programming Language :: Python :: 3 :: Only
Classifier: Operating System :: Unix
Classifier: Operating System :: MacOS :: MacOS X
Classifier: Operating System :: Microsoft :: Windows
License-File: LICENSE
Requires-Dist: requests (==2.*)
